toga_winforms/__init__.py
toga_winforms/app.py
toga_winforms/colors.py
toga_winforms/command.py
toga_winforms/container.py
toga_winforms/dialogs.py
toga_winforms/factory.py
toga_winforms/fonts.py
toga_winforms/icons.py
toga_winforms/images.py
toga_winforms/keys.py
toga_winforms/paths.py
toga_winforms/screens.py
toga_winforms/statusicons.py
toga_winforms/window.py
toga_winforms/hardware/__init__.py
toga_winforms/libs/__init__.py
toga_winforms/libs/extensions.py
toga_winforms/libs/fonts.py
toga_winforms/libs/proactor.py
toga_winforms/libs/wrapper.py
toga_winforms/libs/WebView2/LICENSE.md
toga_winforms/libs/WebView2/Microsoft.Web.WebView2.Core.dll
toga_winforms/libs/WebView2/Microsoft.Web.WebView2.WinForms.dll
toga_winforms/libs/WebView2/README.md
toga_winforms/libs/WebView2/runtimes/win-arm64/native/WebView2Loader.dll
toga_winforms/libs/WebView2/runtimes/win-x64/native/WebView2Loader.dll
toga_winforms/libs/WebView2/runtimes/win-x86/native/WebView2Loader.dll
toga_winforms/resources/toga.ico
toga_winforms/widgets/__init__.py
toga_winforms/widgets/base.py
toga_winforms/widgets/box.py
toga_winforms/widgets/button.py
toga_winforms/widgets/canvas.py
toga_winforms/widgets/dateinput.py
toga_winforms/widgets/detailedlist.py
toga_winforms/widgets/divider.py
toga_winforms/widgets/imageview.py
toga_winforms/widgets/label.py
toga_winforms/widgets/mapview.py
toga_winforms/widgets/multilinetextinput.py
toga_winforms/widgets/numberinput.py
toga_winforms/widgets/optioncontainer.py
toga_winforms/widgets/passwordinput.py
toga_winforms/widgets/progressbar.py
toga_winforms/widgets/scrollcontainer.py
toga_winforms/widgets/selection.py
toga_winforms/widgets/slider.py
toga_winforms/widgets/splitcontainer.py
toga_winforms/widgets/switch.py
toga_winforms/widgets/table.py
toga_winforms/widgets/textinput.py
toga_winforms/widgets/timeinput.py
toga_winforms/widgets/webview.py
toga_winforms-0.4.9.dist-info/LICENSE
toga_winforms-0.4.9.dist-info/METADATA
toga_winforms-0.4.9.dist-info/WHEEL
toga_winforms-0.4.9.dist-info/entry_points.txt
toga_winforms-0.4.9.dist-info/top_level.txt
toga_winforms-0.4.9.dist-info/RECORD
