Metadata-Version: 2.1
Name: toga-winforms
Version: 0.4.9
Summary: A Windows backend for the Toga widget toolkit using the WinForms API.
Author-email: Russell Keith-Magee <russell@keith-magee.com>
Maintainer-email: BeeWare Team <team@beeware.org>
License: New BSD
Project-URL: Homepage, https://beeware.org/project/projects/libraries/toga/
Project-URL: Funding, https://beeware.org/contributing/membership/
Project-URL: Documentation, https://toga.readthedocs.io/
Project-URL: Tracker, https://github.com/beeware/toga/issues
Project-URL: Source, https://github.com/beeware/toga
Project-URL: Changelog, https://toga.readthedocs.io/en/stable/background/project/releases.html
Keywords: gui,widget,cross-platform,toga,desktop,macOS,cocoa
Classifier: Development Status :: 4 - Beta
Classifier: Intended Audience :: Developers
Classifier: License :: OSI Approved :: BSD License
Classifier: Operating System :: OS Independent
Classifier: Programming Language :: Python :: 3
Classifier: Programming Language :: Python :: 3.9
Classifier: Programming Language :: Python :: 3.10
Classifier: Programming Language :: Python :: 3.11
Classifier: Programming Language :: Python :: 3.12
Classifier: Programming Language :: Python :: 3.13
Classifier: Programming Language :: Python :: 3 :: Only
Classifier: Topic :: Software Development
Classifier: Topic :: Software Development :: User Interfaces
Classifier: Topic :: Software Development :: Widget Sets
Requires-Python: >=3.9
License-File: LICENSE
Requires-Dist: pythonnet >=3.0.0
Requires-Dist: toga-core ==0.4.9
